stackmemory.v
//acts as read ANY, write ANY in terms of read, write presedence
//15 stack entries
`define READ_REQ_BIT  11
`define WRITE_REQ_BIT 12
`define READ_ACK_BIT  13
`define WRITE_ACK_BIT 14

`define READ_PHASE  2'd0
`define EX_PHASE    2'd1
`define WRITE_PHASE 2'd2
module stackMemory
  #(
    parameter loadmemory = 0,
    parameter memoryfile = "mem.dat",
    parameter initialpointer = 0
    )
   (input clk,
    input [14:0] in,
    output reg [14:0] out);
   reg [10:0] 		   mem [15:1];
   reg [3:0] 		   pointer;
   reg [2:0] 		   phase;

   initial begin
      phase = `READ_PHASE;
      pointer = initialpointer;
      out = 0;

      if(loadmemory)
	$readmemb(memoryfile, mem);
      if (pointer > 0) begin
	 out[10:0] = mem[pointer];
      end
   end

   always @(posedge in[`WRITE_ACK_BIT]) begin
      pointer = pointer - 1;
      if(pointer > 0) begin
	 out[10:0] = mem[pointer];
      end
   end

   always @(posedge in[`READ_ACK_BIT]) begin
      pointer = pointer -1;
      if (pointer > 0) begin
	 out[`READ_REQ_BIT] <= 1;
	 out[10:0] <= mem[pointer];
      end
      else
	out[`READ_REQ_BIT] <= 0;
   end

   always @(pointer) begin
      if(pointer < 15)
	out[`WRITE_REQ_BIT] <= 1;
      else
	out[`WRITE_REQ_BIT] <= 0;

      if (pointer > 0)
	out[`READ_REQ_BIT] <= 1;
      else
	out[`READ_REQ_BIT] <= 0;
   end // always @ (pointer)

   always @(posedge clk) begin
     case(phase)
       `READ_PHASE:
	 if(in[`READ_REQ_BIT]) begin
	    if(pointer < 15) begin
	       pointer = pointer + 1;
	       mem[pointer] = in[10:0];
	       out[`READ_ACK_BIT] <= 1;
	    end
	 end
       `EX_PHASE: begin

       end
       `WRITE_PHASE:
	 if(pointer > 0) begin
	    out[10:0] <= mem[pointer];
	    if(in[`WRITE_REQ_BIT]) begin
	       pointer = pointer - 1;
	       out[`WRITE_ACK_BIT] <= 1;
	    end
	 end

     endcase
   end // always @ (posedge clk)

   always @(negedge clk) begin
      if (phase == `WRITE_PHASE) begin
	 out[`READ_ACK_BIT] = 0;
	 out[`WRITE_ACK_BIT] = 0;
      end
      phase = (phase + 1) % 3;
   end


endmodule

stackmemory.t.v
`include "stackmemory.v"
module stackMemoryTestBench
  ();

   reg clk;
   reg dutpassed;
   wire [14:0] out;
   reg [10:0] val;
   reg [14:0]  in;
   reg [3:0]   testcase;
   reg [2:0]   phase;
   reg [5:0]   counter;
   
   
   always #10 clk = !clk;

   stackMemory #( .loadmemory(1), .initialpointer(4)) dut 
     (
      .clk(clk),
      .in(in),
      .out(out)
      );

   
   initial begin
      $dumpfile("test.vcd");
      $dumpvars(0);
      clk <= 0;
      dutpassed <= 1;
      phase <= `READ_PHASE;
      in <= 0;
      testcase <= 0;
      counter <= 1;
      
      #30;//time to cycle clock
      //Test Case 0: check flags
      if(!out[`READ_REQ_BIT] || !out[`WRITE_REQ_BIT] || out[`READ_ACK_BIT] || out[`WRITE_ACK_BIT])
	dutpassed = 0;
      in[`WRITE_REQ_BIT] = 1;
      testcase = 1;
   end

   //Test Case 1: read a value 
   always @(posedge clk) begin
      if(testcase == 1 && phase == `READ_PHASE) begin
	 val <= out[10:0];
	 
	 if(val != 11'b10101110010)
	   dutpassed = 0;
	 in[`WRITE_ACK_BIT] <= 1;
	 in[`WRITE_REQ_BIT] <= 0;
	 
	 testcase = 2;
      end
   end

   //Test Case 2: write a value
   always @(posedge clk) begin
      if(testcase == 2 && phase == `WRITE_PHASE) begin
	 val = 11'hBA;
	 in[10:0] <= val;
	 in[`READ_REQ_BIT] <= 1;
      end
   end

   always @(posedge out[`READ_ACK_BIT]) begin
      if(testcase == 2) begin
	 in[`READ_REQ_BIT] <= 0;
	 
	 testcase = 3;
      end
   end

   //Test Case 3: read that value
   always @(posedge clk) begin
      if(testcase == 3 && phase == `READ_PHASE) begin
	 val = out[10:0];
	 
	 if(val != 11'hBA) begin
	    dutpassed = 0;
	 end
	 else begin
	    in[`WRITE_ACK_BIT] = 1;
	    testcase = 4;
	    in[`WRITE_REQ_BIT] = 1;
	 end
      end
   end

   //Test Case 4: read until empty
   always @(posedge out[`WRITE_ACK_BIT]) begin
      if(testcase == 4)
	 counter = counter +1;
   end

   always @(negedge out[`READ_REQ_BIT]) begin
      if(testcase == 4) begin
	 if(counter == 3) begin
	    in[`WRITE_REQ_BIT] = 0;
	    counter = 0;
	    in[10:0] = counter;
	    in[`READ_REQ_BIT] = 1;
	    testcase = 5;
 	 end
	 else
	   dutpassed = 0;
      end
   end // always @ (negedge out[`READ_REQ_BIT])

   //Test Case 5: write until full
   always @(posedge out[`READ_ACK_BIT]) begin
      if(testcase == 5) begin
	 counter = counter + 1;
	 in[10:0] = counter;
      end
   end

   always @(negedge out[`WRITE_REQ_BIT]) begin
      if(testcase == 5) begin
	 if(counter != 15)
	    dutpassed = 0;
	 else begin
	    $display("DUT Passed");
	    $finish();
	 end
      end
   end
      
   always @(negedge clk) begin
      if (phase == `WRITE_PHASE) begin
	 in[`READ_ACK_BIT] = 0;
	 in[`WRITE_ACK_BIT] = 0;
      end
      phase = (phase + 1) % 3;
   end

   always @(negedge dutpassed) begin
      $display("DUT Failed Test: %d", testcase);
      $finish();
   end

endmodule

test.vcd
$date
	Mon Dec 11 22:36:46 2017
$end
$version
	Icarus Verilog
$end
$timescale
	1s
$end
$scope module stackMemoryTestBench $end
$var wire 15 ! out [14:0] $end
$var reg 1 " clk $end
$var reg 6 # counter [5:0] $end
$var reg 1 $ dutpassed $end
$var reg 15 % in [14:0] $end
$var reg 3 & phase [2:0] $end
$var reg 4 ' testcase [3:0] $end
$var reg 11 ( val [10:0] $end
$scope module dut $end
$var wire 1 " clk $end
$var wire 15 ) in [14:0] $end
$var reg 15 * out [14:0] $end
$var reg 3 + phase [2:0] $end
$var reg 4 , pointer [3:0] $end
$upscope $end
$upscope $end
$enddefinitions $end
#0
$dumpvars
b100 ,
b1 +
b1110101110010 *
b0 )
bx (
b0 '
b1 &
b0 %
1$
b1 #
0"
b1110101110010 !
$end
#10
1"
#20
b10 &
b10 +
0"
#30
b101110101110010 !
b101110101110010 *
b11 ,
1"
b1 '
b1000000000000 %
b1000000000000 )
#40
b0 +
b1110101110010 !
b1110101110010 *
b0 &
0"
#50
b1110101110110 !
b1110101110110 *
b10 ,
b100000000000000 %
b100000000000000 )
b10101110010 (
b10 '
1"
#60
b1 &
b1 +
0"
#70
1"
#80
b10 +
b10 &
0"
#90
b100100010111010 %
b100100010111010 )
b10111010 (
1"
#100
b0 &
b100010111010 %
b100010111010 )
b0 +
0"
#110
b10111010 %
b10111010 )
b11 '
b11110101110110 !
b11110101110110 *
b11 ,
1"
#120
b1 +
b1 &
0"
#130
1"
#140
b10 &
b10 +
0"
#150
b11100010111010 !
b11100010111010 *
1"
#160
b0 +
b1100010111010 !
b1100010111010 *
b0 &
0"
#170
b1110101110110 !
b1110101110110 *
b10 ,
b100 '
b101000010111010 %
b101000010111010 )
1"
#180
b1 &
b1 +
0"
#190
1"
#200
b10 +
b10 &
0"
#210
b10 #
b101110101110110 !
b101110101110110 *
b1 ,
1"
#220
b0 &
b1000010111010 %
b1000010111010 )
b0 +
b1110101110110 !
b1110101110110 *
0"
#230
1"
#240
b1 +
b1 &
0"
#250
1"
#260
b10 &
b10 +
0"
#270
b101 '
b100000000000 %
b100000000000 )
b0 #
b101000000000000 !
b101000000000000 *
b0 ,
1"
#280
b0 +
b1000000000000 !
b1000000000000 *
b0 &
0"
#290
b100000000001 %
b100000000001 )
b1 #
b11100000000000 !
b11100000000000 *
b1 ,
1"
#300
b1 &
b1 +
0"
#310
1"
#320
b10 +
b10 &
0"
#330
1"
#340
b0 &
b0 +
b1100000000000 !
b1100000000000 *
0"
#350
b100000000010 %
b100000000010 )
b10 #
b11100000000000 !
b11100000000000 *
b10 ,
1"
#360
b1 +
b1 &
0"
#370
1"
#380
b10 &
b10 +
0"
#390
b11100000000001 !
b11100000000001 *
1"
#400
b0 +
b1100000000001 !
b1100000000001 *
b0 &
0"
#410
b100000000011 %
b100000000011 )
b11 #
b11100000000001 !
b11100000000001 *
b11 ,
1"
#420
b1 &
b1 +
0"
#430
1"
#440
b10 +
b10 &
0"
#450
b11100000000010 !
b11100000000010 *
1"
#460
b0 &
b0 +
b1100000000010 !
b1100000000010 *
0"
#470
b100000000100 %
b100000000100 )
b100 #
b11100000000010 !
b11100000000010 *
b100 ,
1"
#480
b1 +
b1 &
0"
#490
1"
#500
b10 &
b10 +
0"
#510
b11100000000011 !
b11100000000011 *
1"
#520
b0 +
b1100000000011 !
b1100000000011 *
b0 &
0"
#530
b100000000101 %
b100000000101 )
b101 #
b11100000000011 !
b11100000000011 *
b101 ,
1"
#540
b1 &
b1 +
0"
#550
1"
#560
b10 +
b10 &
0"
#570
b11100000000100 !
b11100000000100 *
1"
#580
b0 &
b0 +
b1100000000100 !
b1100000000100 *
0"
#590
b100000000110 %
b100000000110 )
b110 #
b11100000000100 !
b11100000000100 *
b110 ,
1"
#600
b1 +
b1 &
0"
#610
1"
#620
b10 &
b10 +
0"
#630
b11100000000101 !
b11100000000101 *
1"
#640
b0 +
b1100000000101 !
b1100000000101 *
b0 &
0"
#650
b100000000111 %
b100000000111 )
b111 #
b11100000000101 !
b11100000000101 *
b111 ,
1"
#660
b1 &
b1 +
0"
#670
1"
#680
b10 +
b10 &
0"
#690
b11100000000110 !
b11100000000110 *
1"
#700
b0 &
b0 +
b1100000000110 !
b1100000000110 *
0"
#710
b100000001000 %
b100000001000 )
b1000 #
b11100000000110 !
b11100000000110 *
b1000 ,
1"
#720
b1 +
b1 &
0"
#730
1"
#740
b10 &
b10 +
0"
#750
b11100000000111 !
b11100000000111 *
1"
#760
b0 +
b1100000000111 !
b1100000000111 *
b0 &
0"
#770
b100000001001 %
b100000001001 )
b1001 #
b11100000000111 !
b11100000000111 *
b1001 ,
1"
#780
b1 &
b1 +
0"
#790
1"
#800
b10 +
b10 &
0"
#810
b11100000001000 !
b11100000001000 *
1"
#820
b0 &
b0 +
b1100000001000 !
b1100000001000 *
0"
#830
b100000001010 %
b100000001010 )
b1010 #
b11100000001000 !
b11100000001000 *
b1010 ,
1"
#840
b1 +
b1 &
0"
#850
1"
#860
b10 &
b10 +
0"
#870
b11100000001001 !
b11100000001001 *
1"
#880
b0 +
b1100000001001 !
b1100000001001 *
b0 &
0"
#890
b100000001011 %
b100000001011 )
b1011 #
b11100000001001 !
b11100000001001 *
b1011 ,
1"
#900
b1 &
b1 +
0"
#910
1"
#920
b10 +
b10 &
0"
#930
b11100000001010 !
b11100000001010 *
1"
#940
b0 &
b0 +
b1100000001010 !
b1100000001010 *
0"
#950
b100000001100 %
b100000001100 )
b1100 #
b11100000001010 !
b11100000001010 *
b1100 ,
1"
#960
b1 +
b1 &
0"
#970
1"
#980
b10 &
b10 +
0"
#990
b11100000001011 !
b11100000001011 *
1"
#1000
b0 +
b1100000001011 !
b1100000001011 *
b0 &
0"
#1010
b100000001101 %
b100000001101 )
b1101 #
b11100000001011 !
b11100000001011 *
b1101 ,
1"
#1020
b1 &
b1 +
0"
#1030
1"
#1040
b10 +
b10 &
0"
#1050
b11100000001100 !
b11100000001100 *
1"
#1060
b0 &
b0 +
b1100000001100 !
b1100000001100 *
0"
#1070
b100000001110 %
b100000001110 )
b1110 #
b11100000001100 !
b11100000001100 *
b1110 ,
1"
#1080
b1 +
b1 &
0"
#1090
1"
#1100
b10 &
b10 +
0"
#1110
b11100000001101 !
b11100000001101 *
1"
#1120
b0 +
b1100000001101 !
b1100000001101 *
b0 &
0"
#1130
b100000001111 %
b100000001111 )
b1111 #
b10100000001101 !
b10100000001101 *
b1111 ,
1"
